{
  "chmov_version": 0.6,
  "pgn": "[Event \"Rated Blitz game\"]\n[Site \"?\"]\n[Date \"2025.05.12\"]\n[Round \"-\"]\n[White \"simpleEval\"]\n[Black \"CPU2006\"]\n[Result \"0-1\"]\n[LichessURL \"https://lichess.org/pPAIO2C1\"]\n[WhiteTitle \"BOT\"]\n[BlackTitle \"BOT\"]\n[WhiteElo \"2302\"]\n[BlackElo \"2633\"]\n[ECO \"A05\"]\n[Opening \"King's Indian Attack\"]\n[TimeControl \"60+3\"]\n[UTCDate \"2025.05.12\"]\n[UTCTime \"06:59:45\"]\n[Termination \"Normal\"]\n[WhiteRatingDiff \"-2\"]\n[BlackRatingDiff \"+1\"]\n\n1. Nf3 d5 2. g3 Nf6 3. Bg2 c5 4. c4 d4 5. Qb3 Nc6 6. h3 e5 7. Qd1 Bd6 8. d3 h6\n9. Bd2 O-O 10. g4 e4 11. dxe4 Nxe4 12. Na3 Re8 13. Kf1 a6 14. Ne1 Bd7 15. Bxe4\nRxe4 16. Nd3 Qf6 17. Qb3 Rae8 18. Nc1 Ne5 19. Rb1 d3 20. Nc2 dxe2+ 21. Nxe2\nNxc4 22. Bg5 hxg5 23. Qc3 Nd2+ 24. Kg1 Rxe2 25. Qxf6 gxf6 26. Rd1 Bc6 27. Rc1\nBg3 28. Rh2 Bxh2+ 29. Kxh2 Rxf2+ 30. Kg1 Rg2+ 31. Kh1 Rxg4+ 32. Kh2 Re2# 0-1",
  "pretty_pgn": {
    "headers": {
      "Event": "Rated Blitz game",
      "Site": "?",
      "Date": "2025.05.12",
      "Round": "-",
      "White": "simpleEval",
      "Black": "CPU2006",
      "Result": "0-1",
      "LichessURL": "https://lichess.org/pPAIO2C1",
      "WhiteTitle": "BOT",
      "BlackTitle": "BOT",
      "WhiteElo": "2302",
      "BlackElo": "2633",
      "ECO": "A05",
      "Opening": "King's Indian Attack",
      "TimeControl": "60+3",
      "UTCDate": "2025.05.12",
      "UTCTime": "06:59:45",
      "Termination": "Normal",
      "WhiteRatingDiff": "-2",
      "BlackRatingDiff": "+1"
    },
    "moves": [
      "Nf3 d5 g3 Nf6 Bg2 c5 c4 d4",
      "Qb3 Nc6 h3 e5 Qd1 Bd6 d3 h6",
      "Bd2 O-O g4 e4 dxe4 Nxe4 Na3 Re8",
      "Kf1 a6 Ne1 Bd7 Bxe4 Rxe4 Nd3 Qf6",
      "Qb3 Rae8 Nc1 Ne5 Rb1 d3 Nc2 dxe2+",
      "Nxe2 Nxc4 Bg5 hxg5 Qc3 Nd2+ Kg1 Rxe2",
      "Qxf6 gxf6 Rd1 Bc6 Rc1 Bg3 Rh2 Bxh2+",
      "Kxh2 Rxf2+ Kg1 Rg2+ Kh1 Rxg4+ Kh2 Re2#"
    ]
  },
  "moves": [
    {
      "turn": 1,
      "color": "w",
      "frsq": "g1",
      "tosq": "f3",
      "piece": "n",
      "xpid": "wn2",
      "san": "Nf3",
      "cxpid": null,
      "prom": null,
      "castle": null,
      "chk": null,
      "enps": null,
      "fen": "rnbqkbnr/pppppppp/8/8/8/5N2/PPPPPPPP/RNBQKB1R b KQkq - 1 1",
      "xfen": [
        [ "br1", "bn1", "bb1", "bq1", "bk1", "bb2", "bn2", "br2" ],
        [ "bp1", "bp2", "bp3", "bp4", "bp5", "bp6", "bp7", "bp8" ],
        [ null, null, null, null, null, null, null, null ],
        [ null, null, null, null, null, null, null, null ],
        [ null, null, null, null, null, null, null, null ],
        [ null, null, null, null, null, "wn2", null, null ],
        [ "wp1", "wp2", "wp3", "wp4", "wp5", "wp6", "wp7", "wp8" ],
        [ "wr1", "wn1", "wb1", "wq1", "wk1", "wb2", null, "wr2" ]
      ]
    },
    {
      "turn": 2,
      "color": "b",
      "frsq": "d7",
      "tosq": "d5",
      "piece": "p",
      "xpid": "bp4",
      "san": "d5",
      "cxpid": null,
      "prom": null,
      "castle": null,
      "chk": null,
      "enps": null,
      "fen": "rnbqkbnr/ppp1pppp/8/3p4/8/5N2/PPPPPPPP/RNBQKB1R w KQkq - 0 2",
      "xfen": [
        [ "br1", "bn1", "bb1", "bq1", "bk1", "bb2", "bn2", "br2" ],
        [ "bp1", "bp2", "bp3", null, "bp5", "bp6", "bp7", "bp8" ],
        [ null, null, null, null, null, null, null, null ],
        [ null, null, null, "bp4", null, null, null, null ],
        [ null, null, null, null, null, null, null, null ],
        [ null, null, null, null, null, "wn2", null, null ],
        [ "wp1", "wp2", "wp3", "wp4", "wp5", "wp6", "wp7", "wp8" ],
        [ "wr1", "wn1", "wb1", "wq1", "wk1", "wb2", null, "wr2" ]
      ]
    },
    {
      "turn": 3,
      "color": "w",
      "frsq": "g2",
      "tosq": "g3",
      "piece": "p",
      "xpid": "wp7",
      "san": "g3",
      "cxpid": null,
      "prom": null,
      "castle": null,
      "chk": null,
      "enps": null,
      "fen": "rnbqkbnr/ppp1pppp/8/3p4/8/5NP1/PPPPPP1P/RNBQKB1R b KQkq - 0 2",
      "xfen": [
        [ "br1", "bn1", "bb1", "bq1", "bk1", "bb2", "bn2", "br2" ],
        [ "bp1", "bp2", "bp3", null, "bp5", "bp6", "bp7", "bp8" ],
        [ null, null, null, null, null, null, null, null ],
        [ null, null, null, "bp4", null, null, null, null ],
        [ null, null, null, null, null, null, null, null ],
        [ null, null, null, null, null, "wn2", "wp7", null ],
        [ "wp1", "wp2", "wp3", "wp4", "wp5", "wp6", null, "wp8" ],
        [ "wr1", "wn1", "wb1", "wq1", "wk1", "wb2", null, "wr2" ]
      ]
    },
    {
      "turn": 4,
      "color": "b",
      "frsq": "g8",
      "tosq": "f6",
      "piece": "n",
      "xpid": "bn2",
      "san": "Nf6",
      "cxpid": null,
      "prom": null,
      "castle": null,
      "chk": null,
      "enps": null,
      "fen": "rnbqkb1r/ppp1pppp/5n2/3p4/8/5NP1/PPPPPP1P/RNBQKB1R w KQkq - 1 3",
      "xfen": [
        [ "br1", "bn1", "bb1", "bq1", "bk1", "bb2", null, "br2" ],
        [ "bp1", "bp2", "bp3", null, "bp5", "bp6", "bp7", "bp8" ],
        [ null, null, null, null, null, "bn2", null, null ],
        [ null, null, null, "bp4", null, null, null, null ],
        [ null, null, null, null, null, null, null, null ],
        [ null, null, null, null, null, "wn2", "wp7", null ],
        [ "wp1", "wp2", "wp3", "wp4", "wp5", "wp6", null, "wp8" ],
        [ "wr1", "wn1", "wb1", "wq1", "wk1", "wb2", null, "wr2" ]
      ]
    },
    {
      "turn": 5,
      "color": "w",
      "frsq": "f1",
      "tosq": "g2",
      "piece": "b",
      "xpid": "wb2",
      "san": "Bg2",
      "cxpid": null,
      "prom": null,
      "castle": null,
      "chk": null,
      "enps": null,
      "fen": "rnbqkb1r/ppp1pppp/5n2/3p4/8/5NP1/PPPPPPBP/RNBQK2R b KQkq - 2 3",
      "xfen": [
        [ "br1", "bn1", "bb1", "bq1", "bk1", "bb2", null, "br2" ],
        [ "bp1", "bp2", "bp3", null, "bp5", "bp6", "bp7", "bp8" ],
        [ null, null, null, null, null, "bn2", null, null ],
        [ null, null, null, "bp4", null, null, null, null ],
        [ null, null, null, null, null, null, null, null ],
        [ null, null, null, null, null, "wn2", "wp7", null ],
        [ "wp1", "wp2", "wp3", "wp4", "wp5", "wp6", "wb2", "wp8" ],
        [ "wr1", "wn1", "wb1", "wq1", "wk1", null, null, "wr2" ]
      ]
    },
    {
      "turn": 6,
      "color": "b",
      "frsq": "c7",
      "tosq": "c5",
      "piece": "p",
      "xpid": "bp3",
      "san": "c5",
      "cxpid": null,
      "prom": null,
      "castle": null,
      "chk": null,
      "enps": null,
      "fen": "rnbqkb1r/pp2pppp/5n2/2pp4/8/5NP1/PPPPPPBP/RNBQK2R w KQkq - 0 4",
      "xfen": [
        [ "br1", "bn1", "bb1", "bq1", "bk1", "bb2", null, "br2" ],
        [ "bp1", "bp2", null, null, "bp5", "bp6", "bp7", "bp8" ],
        [ null, null, null, null, null, "bn2", null, null ],
        [ null, null, "bp3", "bp4", null, null, null, null ],
        [ null, null, null, null, null, null, null, null ],
        [ null, null, null, null, null, "wn2", "wp7", null ],
        [ "wp1", "wp2", "wp3", "wp4", "wp5", "wp6", "wb2", "wp8" ],
        [ "wr1", "wn1", "wb1", "wq1", "wk1", null, null, "wr2" ]
      ]
    },
    {
      "turn": 7,
      "color": "w",
      "frsq": "c2",
      "tosq": "c4",
      "piece": "p",
      "xpid": "wp3",
      "san": "c4",
      "cxpid": null,
      "prom": null,
      "castle": null,
      "chk": null,
      "enps": null,
      "fen": "rnbqkb1r/pp2pppp/5n2/2pp4/2P5/5NP1/PP1PPPBP/RNBQK2R b KQkq - 0 4",
      "xfen": [
        [ "br1", "bn1", "bb1", "bq1", "bk1", "bb2", null, "br2" ],
        [ "bp1", "bp2", null, null, "bp5", "bp6", "bp7", "bp8" ],
        [ null, null, null, null, null, "bn2", null, null ],
        [ null, null, "bp3", "bp4", null, null, null, null ],
        [ null, null, "wp3", null, null, null, null, null ],
        [ null, null, null, null, null, "wn2", "wp7", null ],
        [ "wp1", "wp2", null, "wp4", "wp5", "wp6", "wb2", "wp8" ],
        [ "wr1", "wn1", "wb1", "wq1", "wk1", null, null, "wr2" ]
      ]
    },
    {
      "turn": 8,
      "color": "b",
      "frsq": "d5",
      "tosq": "d4",
      "piece": "p",
      "xpid": "bp4",
      "san": "d4",
      "cxpid": null,
      "prom": null,
      "castle": null,
      "chk": null,
      "enps": null,
      "fen": "rnbqkb1r/pp2pppp/5n2/2p5/2Pp4/5NP1/PP1PPPBP/RNBQK2R w KQkq - 0 5",
      "xfen": [
        [ "br1", "bn1", "bb1", "bq1", "bk1", "bb2", null, "br2" ],
        [ "bp1", "bp2", null, null, "bp5", "bp6", "bp7", "bp8" ],
        [ null, null, null, null, null, "bn2", null, null ],
        [ null, null, "bp3", null, null, null, null, null ],
        [ null, null, "wp3", "bp4", null, null, null, null ],
        [ null, null, null, null, null, "wn2", "wp7", null ],
        [ "wp1", "wp2", null, "wp4", "wp5", "wp6", "wb2", "wp8" ],
        [ "wr1", "wn1", "wb1", "wq1", "wk1", null, null, "wr2" ]
      ]
    },
    {
      "turn": 9,
      "color": "w",
      "frsq": "d1",
      "tosq": "b3",
      "piece": "q",
      "xpid": "wq1",
      "san": "Qb3",
      "cxpid": null,
      "prom": null,
      "castle": null,
      "chk": null,
      "enps": null,
      "fen": "rnbqkb1r/pp2pppp/5n2/2p5/2Pp4/1Q3NP1/PP1PPPBP/RNB1K2R b KQkq - 1 5",
      "xfen": [
        [ "br1", "bn1", "bb1", "bq1", "bk1", "bb2", null, "br2" ],
        [ "bp1", "bp2", null, null, "bp5", "bp6", "bp7", "bp8" ],
        [ null, null, null, null, null, "bn2", null, null ],
        [ null, null, "bp3", null, null, null, null, null ],
        [ null, null, "wp3", "bp4", null, null, null, null ],
        [ null, "wq1", null, null, null, "wn2", "wp7", null ],
        [ "wp1", "wp2", null, "wp4", "wp5", "wp6", "wb2", "wp8" ],
        [ "wr1", "wn1", "wb1", null, "wk1", null, null, "wr2" ]
      ]
    },
    {
      "turn": 10,
      "color": "b",
      "frsq": "b8",
      "tosq": "c6",
      "piece": "n",
      "xpid": "bn1",
      "san": "Nc6",
      "cxpid": null,
      "prom": null,
      "castle": null,
      "chk": null,
      "enps": null,
      "fen": "r1bqkb1r/pp2pppp/2n2n2/2p5/2Pp4/1Q3NP1/PP1PPPBP/RNB1K2R w KQkq - 2 6",
      "xfen": [
        [ "br1", null, "bb1", "bq1", "bk1", "bb2", null, "br2" ],
        [ "bp1", "bp2", null, null, "bp5", "bp6", "bp7", "bp8" ],
        [ null, null, "bn1", null, null, "bn2", null, null ],
        [ null, null, "bp3", null, null, null, null, null ],
        [ null, null, "wp3", "bp4", null, null, null, null ],
        [ null, "wq1", null, null, null, "wn2", "wp7", null ],
        [ "wp1", "wp2", null, "wp4", "wp5", "wp6", "wb2", "wp8" ],
        [ "wr1", "wn1", "wb1", null, "wk1", null, null, "wr2" ]
      ]
    },
    {
      "turn": 11,
      "color": "w",
      "frsq": "h2",
      "tosq": "h3",
      "piece": "p",
      "xpid": "wp8",
      "san": "h3",
      "cxpid": null,
      "prom": null,
      "castle": null,
      "chk": null,
      "enps": null,
      "fen": "r1bqkb1r/pp2pppp/2n2n2/2p5/2Pp4/1Q3NPP/PP1PPPB1/RNB1K2R b KQkq - 0 6",
      "xfen": [
        [ "br1", null, "bb1", "bq1", "bk1", "bb2", null, "br2" ],
        [ "bp1", "bp2", null, null, "bp5", "bp6", "bp7", "bp8" ],
        [ null, null, "bn1", null, null, "bn2", null, null ],
        [ null, null, "bp3", null, null, null, null, null ],
        [ null, null, "wp3", "bp4", null, null, null, null ],
        [ null, "wq1", null, null, null, "wn2", "wp7", "wp8" ],
        [ "wp1", "wp2", null, "wp4", "wp5", "wp6", "wb2", null ],
        [ "wr1", "wn1", "wb1", null, "wk1", null, null, "wr2" ]
      ]
    },
    {
      "turn": 12,
      "color": "b",
      "frsq": "e7",
      "tosq": "e5",
      "piece": "p",
      "xpid": "bp5",
      "san": "e5",
      "cxpid": null,
      "prom": null,
      "castle": null,
      "chk": null,
      "enps": null,
      "fen": "r1bqkb1r/pp3ppp/2n2n2/2p1p3/2Pp4/1Q3NPP/PP1PPPB1/RNB1K2R w KQkq - 0 7",
      "xfen": [
        [ "br1", null, "bb1", "bq1", "bk1", "bb2", null, "br2" ],
        [ "bp1", "bp2", null, null, null, "bp6", "bp7", "bp8" ],
        [ null, null, "bn1", null, null, "bn2", null, null ],
        [ null, null, "bp3", null, "bp5", null, null, null ],
        [ null, null, "wp3", "bp4", null, null, null, null ],
        [ null, "wq1", null, null, null, "wn2", "wp7", "wp8" ],
        [ "wp1", "wp2", null, "wp4", "wp5", "wp6", "wb2", null ],
        [ "wr1", "wn1", "wb1", null, "wk1", null, null, "wr2" ]
      ]
    },
    {
      "turn": 13,
      "color": "w",
      "frsq": "b3",
      "tosq": "d1",
      "piece": "q",
      "xpid": "wq1",
      "san": "Qd1",
      "cxpid": null,
      "prom": null,
      "castle": null,
      "chk": null,
      "enps": null,
      "fen": "r1bqkb1r/pp3ppp/2n2n2/2p1p3/2Pp4/5NPP/PP1PPPB1/RNBQK2R b KQkq - 1 7",
      "xfen": [
        [ "br1", null, "bb1", "bq1", "bk1", "bb2", null, "br2" ],
        [ "bp1", "bp2", null, null, null, "bp6", "bp7", "bp8" ],
        [ null, null, "bn1", null, null, "bn2", null, null ],
        [ null, null, "bp3", null, "bp5", null, null, null ],
        [ null, null, "wp3", "bp4", null, null, null, null ],
        [ null, null, null, null, null, "wn2", "wp7", "wp8" ],
        [ "wp1", "wp2", null, "wp4", "wp5", "wp6", "wb2", null ],
        [ "wr1", "wn1", "wb1", "wq1", "wk1", null, null, "wr2" ]
      ]
    },
    {
      "turn": 14,
      "color": "b",
      "frsq": "f8",
      "tosq": "d6",
      "piece": "b",
      "xpid": "bb2",
      "san": "Bd6",
      "cxpid": null,
      "prom": null,
      "castle": null,
      "chk": null,
      "enps": null,
      "fen": "r1bqk2r/pp3ppp/2nb1n2/2p1p3/2Pp4/5NPP/PP1PPPB1/RNBQK2R w KQkq - 2 8",
      "xfen": [
        [ "br1", null, "bb1", "bq1", "bk1", null, null, "br2" ],
        [ "bp1", "bp2", null, null, null, "bp6", "bp7", "bp8" ],
        [ null, null, "bn1", "bb2", null, "bn2", null, null ],
        [ null, null, "bp3", null, "bp5", null, null, null ],
        [ null, null, "wp3", "bp4", null, null, null, null ],
        [ null, null, null, null, null, "wn2", "wp7", "wp8" ],
        [ "wp1", "wp2", null, "wp4", "wp5", "wp6", "wb2", null ],
        [ "wr1", "wn1", "wb1", "wq1", "wk1", null, null, "wr2" ]
      ]
    },
    {
      "turn": 15,
      "color": "w",
      "frsq": "d2",
      "tosq": "d3",
      "piece": "p",
      "xpid": "wp4",
      "san": "d3",
      "cxpid": null,
      "prom": null,
      "castle": null,
      "chk": null,
      "enps": null,
      "fen": "r1bqk2r/pp3ppp/2nb1n2/2p1p3/2Pp4/3P1NPP/PP2PPB1/RNBQK2R b KQkq - 0 8",
      "xfen": [
        [ "br1", null, "bb1", "bq1", "bk1", null, null, "br2" ],
        [ "bp1", "bp2", null, null, null, "bp6", "bp7", "bp8" ],
        [ null, null, "bn1", "bb2", null, "bn2", null, null ],
        [ null, null, "bp3", null, "bp5", null, null, null ],
        [ null, null, "wp3", "bp4", null, null, null, null ],
        [ null, null, null, "wp4", null, "wn2", "wp7", "wp8" ],
        [ "wp1", "wp2", null, null, "wp5", "wp6", "wb2", null ],
        [ "wr1", "wn1", "wb1", "wq1", "wk1", null, null, "wr2" ]
      ]
    },
    {
      "turn": 16,
      "color": "b",
      "frsq": "h7",
      "tosq": "h6",
      "piece": "p",
      "xpid": "bp8",
      "san": "h6",
      "cxpid": null,
      "prom": null,
      "castle": null,
      "chk": null,
      "enps": null,
      "fen": "r1bqk2r/pp3pp1/2nb1n1p/2p1p3/2Pp4/3P1NPP/PP2PPB1/RNBQK2R w KQkq - 0 9",
      "xfen": [
        [ "br1", null, "bb1", "bq1", "bk1", null, null, "br2" ],
        [ "bp1", "bp2", null, null, null, "bp6", "bp7", null ],
        [ null, null, "bn1", "bb2", null, "bn2", null, "bp8" ],
        [ null, null, "bp3", null, "bp5", null, null, null ],
        [ null, null, "wp3", "bp4", null, null, null, null ],
        [ null, null, null, "wp4", null, "wn2", "wp7", "wp8" ],
        [ "wp1", "wp2", null, null, "wp5", "wp6", "wb2", null ],
        [ "wr1", "wn1", "wb1", "wq1", "wk1", null, null, "wr2" ]
      ]
    },
    {
      "turn": 17,
      "color": "w",
      "frsq": "c1",
      "tosq": "d2",
      "piece": "b",
      "xpid": "wb1",
      "san": "Bd2",
      "cxpid": null,
      "prom": null,
      "castle": null,
      "chk": null,
      "enps": null,
      "fen": "r1bqk2r/pp3pp1/2nb1n1p/2p1p3/2Pp4/3P1NPP/PP1BPPB1/RN1QK2R b KQkq - 1 9",
      "xfen": [
        [ "br1", null, "bb1", "bq1", "bk1", null, null, "br2" ],
        [ "bp1", "bp2", null, null, null, "bp6", "bp7", null ],
        [ null, null, "bn1", "bb2", null, "bn2", null, "bp8" ],
        [ null, null, "bp3", null, "bp5", null, null, null ],
        [ null, null, "wp3", "bp4", null, null, null, null ],
        [ null, null, null, "wp4", null, "wn2", "wp7", "wp8" ],
        [ "wp1", "wp2", null, "wb1", "wp5", "wp6", "wb2", null ],
        [ "wr1", "wn1", null, "wq1", "wk1", null, null, "wr2" ]
      ]
    },
    {
      "turn": 18,
      "color": "b",
      "frsq": "e8",
      "tosq": "g8",
      "piece": "k",
      "xpid": "bk1",
      "san": "O-O",
      "cxpid": null,
      "prom": null,
      "castle": "f8",
      "chk": null,
      "enps": null,
      "fen": "r1bq1rk1/pp3pp1/2nb1n1p/2p1p3/2Pp4/3P1NPP/PP1BPPB1/RN1QK2R w KQ - 2 10",
      "xfen": [
        [ "br1", null, "bb1", "bq1", null, "br2", "bk1", null ],
        [ "bp1", "bp2", null, null, null, "bp6", "bp7", null ],
        [ null, null, "bn1", "bb2", null, "bn2", null, "bp8" ],
        [ null, null, "bp3", null, "bp5", null, null, null ],
        [ null, null, "wp3", "bp4", null, null, null, null ],
        [ null, null, null, "wp4", null, "wn2", "wp7", "wp8" ],
        [ "wp1", "wp2", null, "wb1", "wp5", "wp6", "wb2", null ],
        [ "wr1", "wn1", null, "wq1", "wk1", null, null, "wr2" ]
      ]
    },
    {
      "turn": 19,
      "color": "w",
      "frsq": "g3",
      "tosq": "g4",
      "piece": "p",
      "xpid": "wp7",
      "san": "g4",
      "cxpid": null,
      "prom": null,
      "castle": null,
      "chk": null,
      "enps": null,
      "fen": "r1bq1rk1/pp3pp1/2nb1n1p/2p1p3/2Pp2P1/3P1N1P/PP1BPPB1/RN1QK2R b KQ - 0 10",
      "xfen": [
        [ "br1", null, "bb1", "bq1", null, "br2", "bk1", null ],
        [ "bp1", "bp2", null, null, null, "bp6", "bp7", null ],
        [ null, null, "bn1", "bb2", null, "bn2", null, "bp8" ],
        [ null, null, "bp3", null, "bp5", null, null, null ],
        [ null, null, "wp3", "bp4", null, null, "wp7", null ],
        [ null, null, null, "wp4", null, "wn2", null, "wp8" ],
        [ "wp1", "wp2", null, "wb1", "wp5", "wp6", "wb2", null ],
        [ "wr1", "wn1", null, "wq1", "wk1", null, null, "wr2" ]
      ]
    },
    {
      "turn": 20,
      "color": "b",
      "frsq": "e5",
      "tosq": "e4",
      "piece": "p",
      "xpid": "bp5",
      "san": "e4",
      "cxpid": null,
      "prom": null,
      "castle": null,
      "chk": null,
      "enps": null,
      "fen": "r1bq1rk1/pp3pp1/2nb1n1p/2p5/2Ppp1P1/3P1N1P/PP1BPPB1/RN1QK2R w KQ - 0 11",
      "xfen": [
        [ "br1", null, "bb1", "bq1", null, "br2", "bk1", null ],
        [ "bp1", "bp2", null, null, null, "bp6", "bp7", null ],
        [ null, null, "bn1", "bb2", null, "bn2", null, "bp8" ],
        [ null, null, "bp3", null, null, null, null, null ],
        [ null, null, "wp3", "bp4", "bp5", null, "wp7", null ],
        [ null, null, null, "wp4", null, "wn2", null, "wp8" ],
        [ "wp1", "wp2", null, "wb1", "wp5", "wp6", "wb2", null ],
        [ "wr1", "wn1", null, "wq1", "wk1", null, null, "wr2" ]
      ]
    },
    {
      "turn": 21,
      "color": "w",
      "frsq": "d3",
      "tosq": "e4",
      "piece": "p",
      "xpid": "wp4",
      "san": "dxe4",
      "cxpid": "bp5",
      "prom": null,
      "castle": null,
      "chk": null,
      "enps": null,
      "fen": "r1bq1rk1/pp3pp1/2nb1n1p/2p5/2PpP1P1/5N1P/PP1BPPB1/RN1QK2R b KQ - 0 11",
      "xfen": [
        [ "br1", null, "bb1", "bq1", null, "br2", "bk1", null ],
        [ "bp1", "bp2", null, null, null, "bp6", "bp7", null ],
        [ null, null, "bn1", "bb2", null, "bn2", null, "bp8" ],
        [ null, null, "bp3", null, null, null, null, null ],
        [ null, null, "wp3", "bp4", "wp4", null, "wp7", null ],
        [ null, null, null, null, null, "wn2", null, "wp8" ],
        [ "wp1", "wp2", null, "wb1", "wp5", "wp6", "wb2", null ],
        [ "wr1", "wn1", null, "wq1", "wk1", null, null, "wr2" ]
      ]
    },
    {
      "turn": 22,
      "color": "b",
      "frsq": "f6",
      "tosq": "e4",
      "piece": "n",
      "xpid": "bn2",
      "san": "Nxe4",
      "cxpid": "wp4",
      "prom": null,
      "castle": null,
      "chk": null,
      "enps": null,
      "fen": "r1bq1rk1/pp3pp1/2nb3p/2p5/2Ppn1P1/5N1P/PP1BPPB1/RN1QK2R w KQ - 0 12",
      "xfen": [
        [ "br1", null, "bb1", "bq1", null, "br2", "bk1", null ],
        [ "bp1", "bp2", null, null, null, "bp6", "bp7", null ],
        [ null, null, "bn1", "bb2", null, null, null, "bp8" ],
        [ null, null, "bp3", null, null, null, null, null ],
        [ null, null, "wp3", "bp4", "bn2", null, "wp7", null ],
        [ null, null, null, null, null, "wn2", null, "wp8" ],
        [ "wp1", "wp2", null, "wb1", "wp5", "wp6", "wb2", null ],
        [ "wr1", "wn1", null, "wq1", "wk1", null, null, "wr2" ]
      ]
    },
    {
      "turn": 23,
      "color": "w",
      "frsq": "b1",
      "tosq": "a3",
      "piece": "n",
      "xpid": "wn1",
      "san": "Na3",
      "cxpid": null,
      "prom": null,
      "castle": null,
      "chk": null,
      "enps": null,
      "fen": "r1bq1rk1/pp3pp1/2nb3p/2p5/2Ppn1P1/N4N1P/PP1BPPB1/R2QK2R b KQ - 1 12",
      "xfen": [
        [ "br1", null, "bb1", "bq1", null, "br2", "bk1", null ],
        [ "bp1", "bp2", null, null, null, "bp6", "bp7", null ],
        [ null, null, "bn1", "bb2", null, null, null, "bp8" ],
        [ null, null, "bp3", null, null, null, null, null ],
        [ null, null, "wp3", "bp4", "bn2", null, "wp7", null ],
        [ "wn1", null, null, null, null, "wn2", null, "wp8" ],
        [ "wp1", "wp2", null, "wb1", "wp5", "wp6", "wb2", null ],
        [ "wr1", null, null, "wq1", "wk1", null, null, "wr2" ]
      ]
    },
    {
      "turn": 24,
      "color": "b",
      "frsq": "f8",
      "tosq": "e8",
      "piece": "r",
      "xpid": "br2",
      "san": "Re8",
      "cxpid": null,
      "prom": null,
      "castle": null,
      "chk": null,
      "enps": null,
      "fen": "r1bqr1k1/pp3pp1/2nb3p/2p5/2Ppn1P1/N4N1P/PP1BPPB1/R2QK2R w KQ - 2 13",
      "xfen": [
        [ "br1", null, "bb1", "bq1", "br2", null, "bk1", null ],
        [ "bp1", "bp2", null, null, null, "bp6", "bp7", null ],
        [ null, null, "bn1", "bb2", null, null, null, "bp8" ],
        [ null, null, "bp3", null, null, null, null, null ],
        [ null, null, "wp3", "bp4", "bn2", null, "wp7", null ],
        [ "wn1", null, null, null, null, "wn2", null, "wp8" ],
        [ "wp1", "wp2", null, "wb1", "wp5", "wp6", "wb2", null ],
        [ "wr1", null, null, "wq1", "wk1", null, null, "wr2" ]
      ]
    },
    {
      "turn": 25,
      "color": "w",
      "frsq": "e1",
      "tosq": "f1",
      "piece": "k",
      "xpid": "wk1",
      "san": "Kf1",
      "cxpid": null,
      "prom": null,
      "castle": null,
      "chk": null,
      "enps": null,
      "fen": "r1bqr1k1/pp3pp1/2nb3p/2p5/2Ppn1P1/N4N1P/PP1BPPB1/R2Q1K1R b - - 3 13",
      "xfen": [
        [ "br1", null, "bb1", "bq1", "br2", null, "bk1", null ],
        [ "bp1", "bp2", null, null, null, "bp6", "bp7", null ],
        [ null, null, "bn1", "bb2", null, null, null, "bp8" ],
        [ null, null, "bp3", null, null, null, null, null ],
        [ null, null, "wp3", "bp4", "bn2", null, "wp7", null ],
        [ "wn1", null, null, null, null, "wn2", null, "wp8" ],
        [ "wp1", "wp2", null, "wb1", "wp5", "wp6", "wb2", null ],
        [ "wr1", null, null, "wq1", null, "wk1", null, "wr2" ]
      ]
    },
    {
      "turn": 26,
      "color": "b",
      "frsq": "a7",
      "tosq": "a6",
      "piece": "p",
      "xpid": "bp1",
      "san": "a6",
      "cxpid": null,
      "prom": null,
      "castle": null,
      "chk": null,
      "enps": null,
      "fen": "r1bqr1k1/1p3pp1/p1nb3p/2p5/2Ppn1P1/N4N1P/PP1BPPB1/R2Q1K1R w - - 0 14",
      "xfen": [
        [ "br1", null, "bb1", "bq1", "br2", null, "bk1", null ],
        [ null, "bp2", null, null, null, "bp6", "bp7", null ],
        [ "bp1", null, "bn1", "bb2", null, null, null, "bp8" ],
        [ null, null, "bp3", null, null, null, null, null ],
        [ null, null, "wp3", "bp4", "bn2", null, "wp7", null ],
        [ "wn1", null, null, null, null, "wn2", null, "wp8" ],
        [ "wp1", "wp2", null, "wb1", "wp5", "wp6", "wb2", null ],
        [ "wr1", null, null, "wq1", null, "wk1", null, "wr2" ]
      ]
    },
    {
      "turn": 27,
      "color": "w",
      "frsq": "f3",
      "tosq": "e1",
      "piece": "n",
      "xpid": "wn2",
      "san": "Ne1",
      "cxpid": null,
      "prom": null,
      "castle": null,
      "chk": null,
      "enps": null,
      "fen": "r1bqr1k1/1p3pp1/p1nb3p/2p5/2Ppn1P1/N6P/PP1BPPB1/R2QNK1R b - - 1 14",
      "xfen": [
        [ "br1", null, "bb1", "bq1", "br2", null, "bk1", null ],
        [ null, "bp2", null, null, null, "bp6", "bp7", null ],
        [ "bp1", null, "bn1", "bb2", null, null, null, "bp8" ],
        [ null, null, "bp3", null, null, null, null, null ],
        [ null, null, "wp3", "bp4", "bn2", null, "wp7", null ],
        [ "wn1", null, null, null, null, null, null, "wp8" ],
        [ "wp1", "wp2", null, "wb1", "wp5", "wp6", "wb2", null ],
        [ "wr1", null, null, "wq1", "wn2", "wk1", null, "wr2" ]
      ]
    },
    {
      "turn": 28,
      "color": "b",
      "frsq": "c8",
      "tosq": "d7",
      "piece": "b",
      "xpid": "bb1",
      "san": "Bd7",
      "cxpid": null,
      "prom": null,
      "castle": null,
      "chk": null,
      "enps": null,
      "fen": "r2qr1k1/1p1b1pp1/p1nb3p/2p5/2Ppn1P1/N6P/PP1BPPB1/R2QNK1R w - - 2 15",
      "xfen": [
        [ "br1", null, null, "bq1", "br2", null, "bk1", null ],
        [ null, "bp2", null, "bb1", null, "bp6", "bp7", null ],
        [ "bp1", null, "bn1", "bb2", null, null, null, "bp8" ],
        [ null, null, "bp3", null, null, null, null, null ],
        [ null, null, "wp3", "bp4", "bn2", null, "wp7", null ],
        [ "wn1", null, null, null, null, null, null, "wp8" ],
        [ "wp1", "wp2", null, "wb1", "wp5", "wp6", "wb2", null ],
        [ "wr1", null, null, "wq1", "wn2", "wk1", null, "wr2" ]
      ]
    },
    {
      "turn": 29,
      "color": "w",
      "frsq": "g2",
      "tosq": "e4",
      "piece": "b",
      "xpid": "wb2",
      "san": "Bxe4",
      "cxpid": "bn2",
      "prom": null,
      "castle": null,
      "chk": null,
      "enps": null,
      "fen": "r2qr1k1/1p1b1pp1/p1nb3p/2p5/2PpB1P1/N6P/PP1BPP2/R2QNK1R b - - 0 15",
      "xfen": [
        [ "br1", null, null, "bq1", "br2", null, "bk1", null ],
        [ null, "bp2", null, "bb1", null, "bp6", "bp7", null ],
        [ "bp1", null, "bn1", "bb2", null, null, null, "bp8" ],
        [ null, null, "bp3", null, null, null, null, null ],
        [ null, null, "wp3", "bp4", "wb2", null, "wp7", null ],
        [ "wn1", null, null, null, null, null, null, "wp8" ],
        [ "wp1", "wp2", null, "wb1", "wp5", "wp6", null, null ],
        [ "wr1", null, null, "wq1", "wn2", "wk1", null, "wr2" ]
      ]
    },
    {
      "turn": 30,
      "color": "b",
      "frsq": "e8",
      "tosq": "e4",
      "piece": "r",
      "xpid": "br2",
      "san": "Rxe4",
      "cxpid": "wb2",
      "prom": null,
      "castle": null,
      "chk": null,
      "enps": null,
      "fen": "r2q2k1/1p1b1pp1/p1nb3p/2p5/2Ppr1P1/N6P/PP1BPP2/R2QNK1R w - - 0 16",
      "xfen": [
        [ "br1", null, null, "bq1", null, null, "bk1", null ],
        [ null, "bp2", null, "bb1", null, "bp6", "bp7", null ],
        [ "bp1", null, "bn1", "bb2", null, null, null, "bp8" ],
        [ null, null, "bp3", null, null, null, null, null ],
        [ null, null, "wp3", "bp4", "br2", null, "wp7", null ],
        [ "wn1", null, null, null, null, null, null, "wp8" ],
        [ "wp1", "wp2", null, "wb1", "wp5", "wp6", null, null ],
        [ "wr1", null, null, "wq1", "wn2", "wk1", null, "wr2" ]
      ]
    },
    {
      "turn": 31,
      "color": "w",
      "frsq": "e1",
      "tosq": "d3",
      "piece": "n",
      "xpid": "wn2",
      "san": "Nd3",
      "cxpid": null,
      "prom": null,
      "castle": null,
      "chk": null,
      "enps": null,
      "fen": "r2q2k1/1p1b1pp1/p1nb3p/2p5/2Ppr1P1/N2N3P/PP1BPP2/R2Q1K1R b - - 1 16",
      "xfen": [
        [ "br1", null, null, "bq1", null, null, "bk1", null ],
        [ null, "bp2", null, "bb1", null, "bp6", "bp7", null ],
        [ "bp1", null, "bn1", "bb2", null, null, null, "bp8" ],
        [ null, null, "bp3", null, null, null, null, null ],
        [ null, null, "wp3", "bp4", "br2", null, "wp7", null ],
        [ "wn1", null, null, "wn2", null, null, null, "wp8" ],
        [ "wp1", "wp2", null, "wb1", "wp5", "wp6", null, null ],
        [ "wr1", null, null, "wq1", null, "wk1", null, "wr2" ]
      ]
    },
    {
      "turn": 32,
      "color": "b",
      "frsq": "d8",
      "tosq": "f6",
      "piece": "q",
      "xpid": "bq1",
      "san": "Qf6",
      "cxpid": null,
      "prom": null,
      "castle": null,
      "chk": null,
      "enps": null,
      "fen": "r5k1/1p1b1pp1/p1nb1q1p/2p5/2Ppr1P1/N2N3P/PP1BPP2/R2Q1K1R w - - 2 17",
      "xfen": [
        [ "br1", null, null, null, null, null, "bk1", null ],
        [ null, "bp2", null, "bb1", null, "bp6", "bp7", null ],
        [ "bp1", null, "bn1", "bb2", null, "bq1", null, "bp8" ],
        [ null, null, "bp3", null, null, null, null, null ],
        [ null, null, "wp3", "bp4", "br2", null, "wp7", null ],
        [ "wn1", null, null, "wn2", null, null, null, "wp8" ],
        [ "wp1", "wp2", null, "wb1", "wp5", "wp6", null, null ],
        [ "wr1", null, null, "wq1", null, "wk1", null, "wr2" ]
      ]
    },
    {
      "turn": 33,
      "color": "w",
      "frsq": "d1",
      "tosq": "b3",
      "piece": "q",
      "xpid": "wq1",
      "san": "Qb3",
      "cxpid": null,
      "prom": null,
      "castle": null,
      "chk": null,
      "enps": null,
      "fen": "r5k1/1p1b1pp1/p1nb1q1p/2p5/2Ppr1P1/NQ1N3P/PP1BPP2/R4K1R b - - 3 17",
      "xfen": [
        [ "br1", null, null, null, null, null, "bk1", null ],
        [ null, "bp2", null, "bb1", null, "bp6", "bp7", null ],
        [ "bp1", null, "bn1", "bb2", null, "bq1", null, "bp8" ],
        [ null, null, "bp3", null, null, null, null, null ],
        [ null, null, "wp3", "bp4", "br2", null, "wp7", null ],
        [ "wn1", "wq1", null, "wn2", null, null, null, "wp8" ],
        [ "wp1", "wp2", null, "wb1", "wp5", "wp6", null, null ],
        [ "wr1", null, null, null, null, "wk1", null, "wr2" ]
      ]
    },
    {
      "turn": 34,
      "color": "b",
      "frsq": "a8",
      "tosq": "e8",
      "piece": "r",
      "xpid": "br1",
      "san": "Rae8",
      "cxpid": null,
      "prom": null,
      "castle": null,
      "chk": null,
      "enps": null,
      "fen": "4r1k1/1p1b1pp1/p1nb1q1p/2p5/2Ppr1P1/NQ1N3P/PP1BPP2/R4K1R w - - 4 18",
      "xfen": [
        [ null, null, null, null, "br1", null, "bk1", null ],
        [ null, "bp2", null, "bb1", null, "bp6", "bp7", null ],
        [ "bp1", null, "bn1", "bb2", null, "bq1", null, "bp8" ],
        [ null, null, "bp3", null, null, null, null, null ],
        [ null, null, "wp3", "bp4", "br2", null, "wp7", null ],
        [ "wn1", "wq1", null, "wn2", null, null, null, "wp8" ],
        [ "wp1", "wp2", null, "wb1", "wp5", "wp6", null, null ],
        [ "wr1", null, null, null, null, "wk1", null, "wr2" ]
      ]
    },
    {
      "turn": 35,
      "color": "w",
      "frsq": "d3",
      "tosq": "c1",
      "piece": "n",
      "xpid": "wn2",
      "san": "Nc1",
      "cxpid": null,
      "prom": null,
      "castle": null,
      "chk": null,
      "enps": null,
      "fen": "4r1k1/1p1b1pp1/p1nb1q1p/2p5/2Ppr1P1/NQ5P/PP1BPP2/R1N2K1R b - - 5 18",
      "xfen": [
        [ null, null, null, null, "br1", null, "bk1", null ],
        [ null, "bp2", null, "bb1", null, "bp6", "bp7", null ],
        [ "bp1", null, "bn1", "bb2", null, "bq1", null, "bp8" ],
        [ null, null, "bp3", null, null, null, null, null ],
        [ null, null, "wp3", "bp4", "br2", null, "wp7", null ],
        [ "wn1", "wq1", null, null, null, null, null, "wp8" ],
        [ "wp1", "wp2", null, "wb1", "wp5", "wp6", null, null ],
        [ "wr1", null, "wn2", null, null, "wk1", null, "wr2" ]
      ]
    },
    {
      "turn": 36,
      "color": "b",
      "frsq": "c6",
      "tosq": "e5",
      "piece": "n",
      "xpid": "bn1",
      "san": "Ne5",
      "cxpid": null,
      "prom": null,
      "castle": null,
      "chk": null,
      "enps": null,
      "fen": "4r1k1/1p1b1pp1/p2b1q1p/2p1n3/2Ppr1P1/NQ5P/PP1BPP2/R1N2K1R w - - 6 19",
      "xfen": [
        [ null, null, null, null, "br1", null, "bk1", null ],
        [ null, "bp2", null, "bb1", null, "bp6", "bp7", null ],
        [ "bp1", null, null, "bb2", null, "bq1", null, "bp8" ],
        [ null, null, "bp3", null, "bn1", null, null, null ],
        [ null, null, "wp3", "bp4", "br2", null, "wp7", null ],
        [ "wn1", "wq1", null, null, null, null, null, "wp8" ],
        [ "wp1", "wp2", null, "wb1", "wp5", "wp6", null, null ],
        [ "wr1", null, "wn2", null, null, "wk1", null, "wr2" ]
      ]
    },
    {
      "turn": 37,
      "color": "w",
      "frsq": "a1",
      "tosq": "b1",
      "piece": "r",
      "xpid": "wr1",
      "san": "Rb1",
      "cxpid": null,
      "prom": null,
      "castle": null,
      "chk": null,
      "enps": null,
      "fen": "4r1k1/1p1b1pp1/p2b1q1p/2p1n3/2Ppr1P1/NQ5P/PP1BPP2/1RN2K1R b - - 7 19",
      "xfen": [
        [ null, null, null, null, "br1", null, "bk1", null ],
        [ null, "bp2", null, "bb1", null, "bp6", "bp7", null ],
        [ "bp1", null, null, "bb2", null, "bq1", null, "bp8" ],
        [ null, null, "bp3", null, "bn1", null, null, null ],
        [ null, null, "wp3", "bp4", "br2", null, "wp7", null ],
        [ "wn1", "wq1", null, null, null, null, null, "wp8" ],
        [ "wp1", "wp2", null, "wb1", "wp5", "wp6", null, null ],
        [ null, "wr1", "wn2", null, null, "wk1", null, "wr2" ]
      ]
    },
    {
      "turn": 38,
      "color": "b",
      "frsq": "d4",
      "tosq": "d3",
      "piece": "p",
      "xpid": "bp4",
      "san": "d3",
      "cxpid": null,
      "prom": null,
      "castle": null,
      "chk": null,
      "enps": null,
      "fen": "4r1k1/1p1b1pp1/p2b1q1p/2p1n3/2P1r1P1/NQ1p3P/PP1BPP2/1RN2K1R w - - 0 20",
      "xfen": [
        [ null, null, null, null, "br1", null, "bk1", null ],
        [ null, "bp2", null, "bb1", null, "bp6", "bp7", null ],
        [ "bp1", null, null, "bb2", null, "bq1", null, "bp8" ],
        [ null, null, "bp3", null, "bn1", null, null, null ],
        [ null, null, "wp3", null, "br2", null, "wp7", null ],
        [ "wn1", "wq1", null, "bp4", null, null, null, "wp8" ],
        [ "wp1", "wp2", null, "wb1", "wp5", "wp6", null, null ],
        [ null, "wr1", "wn2", null, null, "wk1", null, "wr2" ]
      ]
    },
    {
      "turn": 39,
      "color": "w",
      "frsq": "a3",
      "tosq": "c2",
      "piece": "n",
      "xpid": "wn1",
      "san": "Nc2",
      "cxpid": null,
      "prom": null,
      "castle": null,
      "chk": null,
      "enps": null,
      "fen": "4r1k1/1p1b1pp1/p2b1q1p/2p1n3/2P1r1P1/1Q1p3P/PPNBPP2/1RN2K1R b - - 1 20",
      "xfen": [
        [ null, null, null, null, "br1", null, "bk1", null ],
        [ null, "bp2", null, "bb1", null, "bp6", "bp7", null ],
        [ "bp1", null, null, "bb2", null, "bq1", null, "bp8" ],
        [ null, null, "bp3", null, "bn1", null, null, null ],
        [ null, null, "wp3", null, "br2", null, "wp7", null ],
        [ null, "wq1", null, "bp4", null, null, null, "wp8" ],
        [ "wp1", "wp2", "wn1", "wb1", "wp5", "wp6", null, null ],
        [ null, "wr1", "wn2", null, null, "wk1", null, "wr2" ]
      ]
    },
    {
      "turn": 40,
      "color": "b",
      "frsq": "d3",
      "tosq": "e2",
      "piece": "p",
      "xpid": "bp4",
      "san": "dxe2+",
      "cxpid": "wp5",
      "prom": null,
      "castle": null,
      "chk": "+",
      "enps": null,
      "fen": "4r1k1/1p1b1pp1/p2b1q1p/2p1n3/2P1r1P1/1Q5P/PPNBpP2/1RN2K1R w - - 0 21",
      "xfen": [
        [ null, null, null, null, "br1", null, "bk1", null ],
        [ null, "bp2", null, "bb1", null, "bp6", "bp7", null ],
        [ "bp1", null, null, "bb2", null, "bq1", null, "bp8" ],
        [ null, null, "bp3", null, "bn1", null, null, null ],
        [ null, null, "wp3", null, "br2", null, "wp7", null ],
        [ null, "wq1", null, null, null, null, null, "wp8" ],
        [ "wp1", "wp2", "wn1", "wb1", "bp4", "wp6", null, null ],
        [ null, "wr1", "wn2", null, null, "wk1", null, "wr2" ]
      ]
    },
    {
      "turn": 41,
      "color": "w",
      "frsq": "c1",
      "tosq": "e2",
      "piece": "n",
      "xpid": "wn2",
      "san": "Nxe2",
      "cxpid": "bp4",
      "prom": null,
      "castle": null,
      "chk": null,
      "enps": null,
      "fen": "4r1k1/1p1b1pp1/p2b1q1p/2p1n3/2P1r1P1/1Q5P/PPNBNP2/1R3K1R b - - 0 21",
      "xfen": [
        [ null, null, null, null, "br1", null, "bk1", null ],
        [ null, "bp2", null, "bb1", null, "bp6", "bp7", null ],
        [ "bp1", null, null, "bb2", null, "bq1", null, "bp8" ],
        [ null, null, "bp3", null, "bn1", null, null, null ],
        [ null, null, "wp3", null, "br2", null, "wp7", null ],
        [ null, "wq1", null, null, null, null, null, "wp8" ],
        [ "wp1", "wp2", "wn1", "wb1", "wn2", "wp6", null, null ],
        [ null, "wr1", null, null, null, "wk1", null, "wr2" ]
      ]
    },
    {
      "turn": 42,
      "color": "b",
      "frsq": "e5",
      "tosq": "c4",
      "piece": "n",
      "xpid": "bn1",
      "san": "Nxc4",
      "cxpid": "wp3",
      "prom": null,
      "castle": null,
      "chk": null,
      "enps": null,
      "fen": "4r1k1/1p1b1pp1/p2b1q1p/2p5/2n1r1P1/1Q5P/PPNBNP2/1R3K1R w - - 0 22",
      "xfen": [
        [ null, null, null, null, "br1", null, "bk1", null ],
        [ null, "bp2", null, "bb1", null, "bp6", "bp7", null ],
        [ "bp1", null, null, "bb2", null, "bq1", null, "bp8" ],
        [ null, null, "bp3", null, null, null, null, null ],
        [ null, null, "bn1", null, "br2", null, "wp7", null ],
        [ null, "wq1", null, null, null, null, null, "wp8" ],
        [ "wp1", "wp2", "wn1", "wb1", "wn2", "wp6", null, null ],
        [ null, "wr1", null, null, null, "wk1", null, "wr2" ]
      ]
    },
    {
      "turn": 43,
      "color": "w",
      "frsq": "d2",
      "tosq": "g5",
      "piece": "b",
      "xpid": "wb1",
      "san": "Bg5",
      "cxpid": null,
      "prom": null,
      "castle": null,
      "chk": null,
      "enps": null,
      "fen": "4r1k1/1p1b1pp1/p2b1q1p/2p3B1/2n1r1P1/1Q5P/PPN1NP2/1R3K1R b - - 1 22",
      "xfen": [
        [ null, null, null, null, "br1", null, "bk1", null ],
        [ null, "bp2", null, "bb1", null, "bp6", "bp7", null ],
        [ "bp1", null, null, "bb2", null, "bq1", null, "bp8" ],
        [ null, null, "bp3", null, null, null, "wb1", null ],
        [ null, null, "bn1", null, "br2", null, "wp7", null ],
        [ null, "wq1", null, null, null, null, null, "wp8" ],
        [ "wp1", "wp2", "wn1", null, "wn2", "wp6", null, null ],
        [ null, "wr1", null, null, null, "wk1", null, "wr2" ]
      ]
    },
    {
      "turn": 44,
      "color": "b",
      "frsq": "h6",
      "tosq": "g5",
      "piece": "p",
      "xpid": "bp8",
      "san": "hxg5",
      "cxpid": "wb1",
      "prom": null,
      "castle": null,
      "chk": null,
      "enps": null,
      "fen": "4r1k1/1p1b1pp1/p2b1q2/2p3p1/2n1r1P1/1Q5P/PPN1NP2/1R3K1R w - - 0 23",
      "xfen": [
        [ null, null, null, null, "br1", null, "bk1", null ],
        [ null, "bp2", null, "bb1", null, "bp6", "bp7", null ],
        [ "bp1", null, null, "bb2", null, "bq1", null, null ],
        [ null, null, "bp3", null, null, null, "bp8", null ],
        [ null, null, "bn1", null, "br2", null, "wp7", null ],
        [ null, "wq1", null, null, null, null, null, "wp8" ],
        [ "wp1", "wp2", "wn1", null, "wn2", "wp6", null, null ],
        [ null, "wr1", null, null, null, "wk1", null, "wr2" ]
      ]
    },
    {
      "turn": 45,
      "color": "w",
      "frsq": "b3",
      "tosq": "c3",
      "piece": "q",
      "xpid": "wq1",
      "san": "Qc3",
      "cxpid": null,
      "prom": null,
      "castle": null,
      "chk": null,
      "enps": null,
      "fen": "4r1k1/1p1b1pp1/p2b1q2/2p3p1/2n1r1P1/2Q4P/PPN1NP2/1R3K1R b - - 1 23",
      "xfen": [
        [ null, null, null, null, "br1", null, "bk1", null ],
        [ null, "bp2", null, "bb1", null, "bp6", "bp7", null ],
        [ "bp1", null, null, "bb2", null, "bq1", null, null ],
        [ null, null, "bp3", null, null, null, "bp8", null ],
        [ null, null, "bn1", null, "br2", null, "wp7", null ],
        [ null, null, "wq1", null, null, null, null, "wp8" ],
        [ "wp1", "wp2", "wn1", null, "wn2", "wp6", null, null ],
        [ null, "wr1", null, null, null, "wk1", null, "wr2" ]
      ]
    },
    {
      "turn": 46,
      "color": "b",
      "frsq": "c4",
      "tosq": "d2",
      "piece": "n",
      "xpid": "bn1",
      "san": "Nd2+",
      "cxpid": null,
      "prom": null,
      "castle": null,
      "chk": "+",
      "enps": null,
      "fen": "4r1k1/1p1b1pp1/p2b1q2/2p3p1/4r1P1/2Q4P/PPNnNP2/1R3K1R w - - 2 24",
      "xfen": [
        [ null, null, null, null, "br1", null, "bk1", null ],
        [ null, "bp2", null, "bb1", null, "bp6", "bp7", null ],
        [ "bp1", null, null, "bb2", null, "bq1", null, null ],
        [ null, null, "bp3", null, null, null, "bp8", null ],
        [ null, null, null, null, "br2", null, "wp7", null ],
        [ null, null, "wq1", null, null, null, null, "wp8" ],
        [ "wp1", "wp2", "wn1", "bn1", "wn2", "wp6", null, null ],
        [ null, "wr1", null, null, null, "wk1", null, "wr2" ]
      ]
    },
    {
      "turn": 47,
      "color": "w",
      "frsq": "f1",
      "tosq": "g1",
      "piece": "k",
      "xpid": "wk1",
      "san": "Kg1",
      "cxpid": null,
      "prom": null,
      "castle": null,
      "chk": null,
      "enps": null,
      "fen": "4r1k1/1p1b1pp1/p2b1q2/2p3p1/4r1P1/2Q4P/PPNnNP2/1R4KR b - - 3 24",
      "xfen": [
        [ null, null, null, null, "br1", null, "bk1", null ],
        [ null, "bp2", null, "bb1", null, "bp6", "bp7", null ],
        [ "bp1", null, null, "bb2", null, "bq1", null, null ],
        [ null, null, "bp3", null, null, null, "bp8", null ],
        [ null, null, null, null, "br2", null, "wp7", null ],
        [ null, null, "wq1", null, null, null, null, "wp8" ],
        [ "wp1", "wp2", "wn1", "bn1", "wn2", "wp6", null, null ],
        [ null, "wr1", null, null, null, null, "wk1", "wr2" ]
      ]
    },
    {
      "turn": 48,
      "color": "b",
      "frsq": "e4",
      "tosq": "e2",
      "piece": "r",
      "xpid": "br2",
      "san": "Rxe2",
      "cxpid": "wn2",
      "prom": null,
      "castle": null,
      "chk": null,
      "enps": null,
      "fen": "4r1k1/1p1b1pp1/p2b1q2/2p3p1/6P1/2Q4P/PPNnrP2/1R4KR w - - 0 25",
      "xfen": [
        [ null, null, null, null, "br1", null, "bk1", null ],
        [ null, "bp2", null, "bb1", null, "bp6", "bp7", null ],
        [ "bp1", null, null, "bb2", null, "bq1", null, null ],
        [ null, null, "bp3", null, null, null, "bp8", null ],
        [ null, null, null, null, null, null, "wp7", null ],
        [ null, null, "wq1", null, null, null, null, "wp8" ],
        [ "wp1", "wp2", "wn1", "bn1", "br2", "wp6", null, null ],
        [ null, "wr1", null, null, null, null, "wk1", "wr2" ]
      ]
    },
    {
      "turn": 49,
      "color": "w",
      "frsq": "c3",
      "tosq": "f6",
      "piece": "q",
      "xpid": "wq1",
      "san": "Qxf6",
      "cxpid": "bq1",
      "prom": null,
      "castle": null,
      "chk": null,
      "enps": null,
      "fen": "4r1k1/1p1b1pp1/p2b1Q2/2p3p1/6P1/7P/PPNnrP2/1R4KR b - - 0 25",
      "xfen": [
        [ null, null, null, null, "br1", null, "bk1", null ],
        [ null, "bp2", null, "bb1", null, "bp6", "bp7", null ],
        [ "bp1", null, null, "bb2", null, "wq1", null, null ],
        [ null, null, "bp3", null, null, null, "bp8", null ],
        [ null, null, null, null, null, null, "wp7", null ],
        [ null, null, null, null, null, null, null, "wp8" ],
        [ "wp1", "wp2", "wn1", "bn1", "br2", "wp6", null, null ],
        [ null, "wr1", null, null, null, null, "wk1", "wr2" ]
      ]
    },
    {
      "turn": 50,
      "color": "b",
      "frsq": "g7",
      "tosq": "f6",
      "piece": "p",
      "xpid": "bp7",
      "san": "gxf6",
      "cxpid": "wq1",
      "prom": null,
      "castle": null,
      "chk": null,
      "enps": null,
      "fen": "4r1k1/1p1b1p2/p2b1p2/2p3p1/6P1/7P/PPNnrP2/1R4KR w - - 0 26",
      "xfen": [
        [ null, null, null, null, "br1", null, "bk1", null ],
        [ null, "bp2", null, "bb1", null, "bp6", null, null ],
        [ "bp1", null, null, "bb2", null, "bp7", null, null ],
        [ null, null, "bp3", null, null, null, "bp8", null ],
        [ null, null, null, null, null, null, "wp7", null ],
        [ null, null, null, null, null, null, null, "wp8" ],
        [ "wp1", "wp2", "wn1", "bn1", "br2", "wp6", null, null ],
        [ null, "wr1", null, null, null, null, "wk1", "wr2" ]
      ]
    },
    {
      "turn": 51,
      "color": "w",
      "frsq": "b1",
      "tosq": "d1",
      "piece": "r",
      "xpid": "wr1",
      "san": "Rd1",
      "cxpid": null,
      "prom": null,
      "castle": null,
      "chk": null,
      "enps": null,
      "fen": "4r1k1/1p1b1p2/p2b1p2/2p3p1/6P1/7P/PPNnrP2/3R2KR b - - 1 26",
      "xfen": [
        [ null, null, null, null, "br1", null, "bk1", null ],
        [ null, "bp2", null, "bb1", null, "bp6", null, null ],
        [ "bp1", null, null, "bb2", null, "bp7", null, null ],
        [ null, null, "bp3", null, null, null, "bp8", null ],
        [ null, null, null, null, null, null, "wp7", null ],
        [ null, null, null, null, null, null, null, "wp8" ],
        [ "wp1", "wp2", "wn1", "bn1", "br2", "wp6", null, null ],
        [ null, null, null, "wr1", null, null, "wk1", "wr2" ]
      ]
    },
    {
      "turn": 52,
      "color": "b",
      "frsq": "d7",
      "tosq": "c6",
      "piece": "b",
      "xpid": "bb1",
      "san": "Bc6",
      "cxpid": null,
      "prom": null,
      "castle": null,
      "chk": null,
      "enps": null,
      "fen": "4r1k1/1p3p2/p1bb1p2/2p3p1/6P1/7P/PPNnrP2/3R2KR w - - 2 27",
      "xfen": [
        [ null, null, null, null, "br1", null, "bk1", null ],
        [ null, "bp2", null, null, null, "bp6", null, null ],
        [ "bp1", null, "bb1", "bb2", null, "bp7", null, null ],
        [ null, null, "bp3", null, null, null, "bp8", null ],
        [ null, null, null, null, null, null, "wp7", null ],
        [ null, null, null, null, null, null, null, "wp8" ],
        [ "wp1", "wp2", "wn1", "bn1", "br2", "wp6", null, null ],
        [ null, null, null, "wr1", null, null, "wk1", "wr2" ]
      ]
    },
    {
      "turn": 53,
      "color": "w",
      "frsq": "d1",
      "tosq": "c1",
      "piece": "r",
      "xpid": "wr1",
      "san": "Rc1",
      "cxpid": null,
      "prom": null,
      "castle": null,
      "chk": null,
      "enps": null,
      "fen": "4r1k1/1p3p2/p1bb1p2/2p3p1/6P1/7P/PPNnrP2/2R3KR b - - 3 27",
      "xfen": [
        [ null, null, null, null, "br1", null, "bk1", null ],
        [ null, "bp2", null, null, null, "bp6", null, null ],
        [ "bp1", null, "bb1", "bb2", null, "bp7", null, null ],
        [ null, null, "bp3", null, null, null, "bp8", null ],
        [ null, null, null, null, null, null, "wp7", null ],
        [ null, null, null, null, null, null, null, "wp8" ],
        [ "wp1", "wp2", "wn1", "bn1", "br2", "wp6", null, null ],
        [ null, null, "wr1", null, null, null, "wk1", "wr2" ]
      ]
    },
    {
      "turn": 54,
      "color": "b",
      "frsq": "d6",
      "tosq": "g3",
      "piece": "b",
      "xpid": "bb2",
      "san": "Bg3",
      "cxpid": null,
      "prom": null,
      "castle": null,
      "chk": null,
      "enps": null,
      "fen": "4r1k1/1p3p2/p1b2p2/2p3p1/6P1/6bP/PPNnrP2/2R3KR w - - 4 28",
      "xfen": [
        [ null, null, null, null, "br1", null, "bk1", null ],
        [ null, "bp2", null, null, null, "bp6", null, null ],
        [ "bp1", null, "bb1", null, null, "bp7", null, null ],
        [ null, null, "bp3", null, null, null, "bp8", null ],
        [ null, null, null, null, null, null, "wp7", null ],
        [ null, null, null, null, null, null, "bb2", "wp8" ],
        [ "wp1", "wp2", "wn1", "bn1", "br2", "wp6", null, null ],
        [ null, null, "wr1", null, null, null, "wk1", "wr2" ]
      ]
    },
    {
      "turn": 55,
      "color": "w",
      "frsq": "h1",
      "tosq": "h2",
      "piece": "r",
      "xpid": "wr2",
      "san": "Rh2",
      "cxpid": null,
      "prom": null,
      "castle": null,
      "chk": null,
      "enps": null,
      "fen": "4r1k1/1p3p2/p1b2p2/2p3p1/6P1/6bP/PPNnrP1R/2R3K1 b - - 5 28",
      "xfen": [
        [ null, null, null, null, "br1", null, "bk1", null ],
        [ null, "bp2", null, null, null, "bp6", null, null ],
        [ "bp1", null, "bb1", null, null, "bp7", null, null ],
        [ null, null, "bp3", null, null, null, "bp8", null ],
        [ null, null, null, null, null, null, "wp7", null ],
        [ null, null, null, null, null, null, "bb2", "wp8" ],
        [ "wp1", "wp2", "wn1", "bn1", "br2", "wp6", null, "wr2" ],
        [ null, null, "wr1", null, null, null, "wk1", null ]
      ]
    },
    {
      "turn": 56,
      "color": "b",
      "frsq": "g3",
      "tosq": "h2",
      "piece": "b",
      "xpid": "bb2",
      "san": "Bxh2+",
      "cxpid": "wr2",
      "prom": null,
      "castle": null,
      "chk": "+",
      "enps": null,
      "fen": "4r1k1/1p3p2/p1b2p2/2p3p1/6P1/7P/PPNnrP1b/2R3K1 w - - 0 29",
      "xfen": [
        [ null, null, null, null, "br1", null, "bk1", null ],
        [ null, "bp2", null, null, null, "bp6", null, null ],
        [ "bp1", null, "bb1", null, null, "bp7", null, null ],
        [ null, null, "bp3", null, null, null, "bp8", null ],
        [ null, null, null, null, null, null, "wp7", null ],
        [ null, null, null, null, null, null, null, "wp8" ],
        [ "wp1", "wp2", "wn1", "bn1", "br2", "wp6", null, "bb2" ],
        [ null, null, "wr1", null, null, null, "wk1", null ]
      ]
    },
    {
      "turn": 57,
      "color": "w",
      "frsq": "g1",
      "tosq": "h2",
      "piece": "k",
      "xpid": "wk1",
      "san": "Kxh2",
      "cxpid": "bb2",
      "prom": null,
      "castle": null,
      "chk": null,
      "enps": null,
      "fen": "4r1k1/1p3p2/p1b2p2/2p3p1/6P1/7P/PPNnrP1K/2R5 b - - 0 29",
      "xfen": [
        [ null, null, null, null, "br1", null, "bk1", null ],
        [ null, "bp2", null, null, null, "bp6", null, null ],
        [ "bp1", null, "bb1", null, null, "bp7", null, null ],
        [ null, null, "bp3", null, null, null, "bp8", null ],
        [ null, null, null, null, null, null, "wp7", null ],
        [ null, null, null, null, null, null, null, "wp8" ],
        [ "wp1", "wp2", "wn1", "bn1", "br2", "wp6", null, "wk1" ],
        [ null, null, "wr1", null, null, null, null, null ]
      ]
    },
    {
      "turn": 58,
      "color": "b",
      "frsq": "e2",
      "tosq": "f2",
      "piece": "r",
      "xpid": "br2",
      "san": "Rxf2+",
      "cxpid": "wp6",
      "prom": null,
      "castle": null,
      "chk": "+",
      "enps": null,
      "fen": "4r1k1/1p3p2/p1b2p2/2p3p1/6P1/7P/PPNn1r1K/2R5 w - - 0 30",
      "xfen": [
        [ null, null, null, null, "br1", null, "bk1", null ],
        [ null, "bp2", null, null, null, "bp6", null, null ],
        [ "bp1", null, "bb1", null, null, "bp7", null, null ],
        [ null, null, "bp3", null, null, null, "bp8", null ],
        [ null, null, null, null, null, null, "wp7", null ],
        [ null, null, null, null, null, null, null, "wp8" ],
        [ "wp1", "wp2", "wn1", "bn1", null, "br2", null, "wk1" ],
        [ null, null, "wr1", null, null, null, null, null ]
      ]
    },
    {
      "turn": 59,
      "color": "w",
      "frsq": "h2",
      "tosq": "g1",
      "piece": "k",
      "xpid": "wk1",
      "san": "Kg1",
      "cxpid": null,
      "prom": null,
      "castle": null,
      "chk": null,
      "enps": null,
      "fen": "4r1k1/1p3p2/p1b2p2/2p3p1/6P1/7P/PPNn1r2/2R3K1 b - - 1 30",
      "xfen": [
        [ null, null, null, null, "br1", null, "bk1", null ],
        [ null, "bp2", null, null, null, "bp6", null, null ],
        [ "bp1", null, "bb1", null, null, "bp7", null, null ],
        [ null, null, "bp3", null, null, null, "bp8", null ],
        [ null, null, null, null, null, null, "wp7", null ],
        [ null, null, null, null, null, null, null, "wp8" ],
        [ "wp1", "wp2", "wn1", "bn1", null, "br2", null, null ],
        [ null, null, "wr1", null, null, null, "wk1", null ]
      ]
    },
    {
      "turn": 60,
      "color": "b",
      "frsq": "f2",
      "tosq": "g2",
      "piece": "r",
      "xpid": "br2",
      "san": "Rg2+",
      "cxpid": null,
      "prom": null,
      "castle": null,
      "chk": "+",
      "enps": null,
      "fen": "4r1k1/1p3p2/p1b2p2/2p3p1/6P1/7P/PPNn2r1/2R3K1 w - - 2 31",
      "xfen": [
        [ null, null, null, null, "br1", null, "bk1", null ],
        [ null, "bp2", null, null, null, "bp6", null, null ],
        [ "bp1", null, "bb1", null, null, "bp7", null, null ],
        [ null, null, "bp3", null, null, null, "bp8", null ],
        [ null, null, null, null, null, null, "wp7", null ],
        [ null, null, null, null, null, null, null, "wp8" ],
        [ "wp1", "wp2", "wn1", "bn1", null, null, "br2", null ],
        [ null, null, "wr1", null, null, null, "wk1", null ]
      ]
    },
    {
      "turn": 61,
      "color": "w",
      "frsq": "g1",
      "tosq": "h1",
      "piece": "k",
      "xpid": "wk1",
      "san": "Kh1",
      "cxpid": null,
      "prom": null,
      "castle": null,
      "chk": null,
      "enps": null,
      "fen": "4r1k1/1p3p2/p1b2p2/2p3p1/6P1/7P/PPNn2r1/2R4K b - - 3 31",
      "xfen": [
        [ null, null, null, null, "br1", null, "bk1", null ],
        [ null, "bp2", null, null, null, "bp6", null, null ],
        [ "bp1", null, "bb1", null, null, "bp7", null, null ],
        [ null, null, "bp3", null, null, null, "bp8", null ],
        [ null, null, null, null, null, null, "wp7", null ],
        [ null, null, null, null, null, null, null, "wp8" ],
        [ "wp1", "wp2", "wn1", "bn1", null, null, "br2", null ],
        [ null, null, "wr1", null, null, null, null, "wk1" ]
      ]
    },
    {
      "turn": 62,
      "color": "b",
      "frsq": "g2",
      "tosq": "g4",
      "piece": "r",
      "xpid": "br2",
      "san": "Rxg4+",
      "cxpid": "wp7",
      "prom": null,
      "castle": null,
      "chk": "+",
      "enps": null,
      "fen": "4r1k1/1p3p2/p1b2p2/2p3p1/6r1/7P/PPNn4/2R4K w - - 0 32",
      "xfen": [
        [ null, null, null, null, "br1", null, "bk1", null ],
        [ null, "bp2", null, null, null, "bp6", null, null ],
        [ "bp1", null, "bb1", null, null, "bp7", null, null ],
        [ null, null, "bp3", null, null, null, "bp8", null ],
        [ null, null, null, null, null, null, "br2", null ],
        [ null, null, null, null, null, null, null, "wp8" ],
        [ "wp1", "wp2", "wn1", "bn1", null, null, null, null ],
        [ null, null, "wr1", null, null, null, null, "wk1" ]
      ]
    },
    {
      "turn": 63,
      "color": "w",
      "frsq": "h1",
      "tosq": "h2",
      "piece": "k",
      "xpid": "wk1",
      "san": "Kh2",
      "cxpid": null,
      "prom": null,
      "castle": null,
      "chk": null,
      "enps": null,
      "fen": "4r1k1/1p3p2/p1b2p2/2p3p1/6r1/7P/PPNn3K/2R5 b - - 1 32",
      "xfen": [
        [ null, null, null, null, "br1", null, "bk1", null ],
        [ null, "bp2", null, null, null, "bp6", null, null ],
        [ "bp1", null, "bb1", null, null, "bp7", null, null ],
        [ null, null, "bp3", null, null, null, "bp8", null ],
        [ null, null, null, null, null, null, "br2", null ],
        [ null, null, null, null, null, null, null, "wp8" ],
        [ "wp1", "wp2", "wn1", "bn1", null, null, null, "wk1" ],
        [ null, null, "wr1", null, null, null, null, null ]
      ]
    },
    {
      "turn": 64,
      "color": "b",
      "frsq": "e8",
      "tosq": "e2",
      "piece": "r",
      "xpid": "br1",
      "san": "Re2#",
      "cxpid": null,
      "prom": null,
      "castle": null,
      "chk": "+",
      "enps": null,
      "fen": "6k1/1p3p2/p1b2p2/2p3p1/6r1/7P/PPNnr2K/2R5 w - - 2 33",
      "xfen": [
        [ null, null, null, null, null, null, "bk1", null ],
        [ null, "bp2", null, null, null, "bp6", null, null ],
        [ "bp1", null, "bb1", null, null, "bp7", null, null ],
        [ null, null, "bp3", null, null, null, "bp8", null ],
        [ null, null, null, null, null, null, "br2", null ],
        [ null, null, null, null, null, null, null, "wp8" ],
        [ "wp1", "wp2", "wn1", "bn1", "br1", null, null, "wk1" ],
        [ null, null, "wr1", null, null, null, null, null ]
      ]
    }
  ]
}